get_input/__init__.py
get_input-0.0.1.dist-info/METADATA
get_input-0.0.1.dist-info/RECORD
get_input-0.0.1.dist-info/WHEEL
get_input-0.0.1.dist-info/top_level.txt
