Metadata-Version: 2.1
Name: get-input
Version: 0.0.1
Summary: This package allows program to get data iput of a specific type without giving errors
Home-page: https://github.com/yoptgyo/get_input
Author: Prashant Sengar
Author-email: prashantsengar5@hotmail.com
License: UNKNOWN
Platform: UNKNOWN
Classifier: Programming Language :: Python :: 3
Classifier: License :: OSI Approved :: MIT License
Classifier: Operating System :: OS Independent
